MANIFEST.in
README.md
setup.py
soundnet/__init__.py
soundnet.egg-info/PKG-INFO
soundnet.egg-info/SOURCES.txt
soundnet.egg-info/dependency_links.txt
soundnet.egg-info/requires.txt
soundnet.egg-info/top_level.txt
soundnet/models/sound8.npy