Metadata-Version: 1.0
Name: soundnet
Version: 0.1.2
Summary: sound classification with SoundNet
Home-page: https://github.com/JarbasAl/soundnet
Author: jarbasAI
Author-email: jarbasai@mailfence.com
License: MIT
Platform: UNKNOWN
